setup.py
Pyder.egg-info/PKG-INFO
Pyder.egg-info/SOURCES.txt
Pyder.egg-info/dependency_links.txt
Pyder.egg-info/top_level.txt
pyder.egg-info/SOURCES.txt
python/__init__.py
python/builder.py
python/main.py
python/post_builder.py