Metadata-Version: 1.1
Name: pyder
Version: 0.0.1
Summary: A static website generator written in Python!
Home-page: https://github.com/HoughIO/Pyder
Author: HoughIO and ewmiller
Author-email: UNKNOWN
License: BSD 3-Clause
Keywords: pyder python spider website development blog maker builder
Platform: UNKNOWN
Classifier: Development Status :: 2 - Pre-Alpha
Classifier: Intended Audience :: End Users/Desktop
Classifier: Topic :: Software Development :: Build Tools
Classifier: License :: OSI Approved :: BSD License
Classifier: Programming Language :: Python :: 3.5
